tlem/.git
tlem/.gitattributes
tlem/.gitignore
tlem/README.md
tlem/index.html
tlem/style.css
tlem/tasks.py
tlem/tlem.py
tlem/utils.py
tlem-0.1.0.dist-info/METADATA
tlem-0.1.0.dist-info/WHEEL
tlem-0.1.0.dist-info/RECORD
